setup.py
theano_bpr/__init__.py
theano_bpr/bpr.py
theano_bpr/t.py
theano_bpr/utils.py
theano_bpr.egg-info/PKG-INFO
theano_bpr.egg-info/SOURCES.txt
theano_bpr.egg-info/dependency_links.txt
theano_bpr.egg-info/requires.txt
theano_bpr.egg-info/top_level.txt