Metadata-Version: 1.0
Name: theano-bpr
Version: 0.1.1
Summary: Bayesian Personalised Ranking implemented in Theano
Home-page: https://github.com/bbcrd/theano-bpr
Author: Yves Raimond
Author-email: yves.raimond@bbc.co.uk
License: Apache License 2.0
Platform: UNKNOWN
